molgenis_emx2/directory_client/__init__.py
molgenis_emx2/directory_client/categories.py
molgenis_emx2/directory_client/directory.py
molgenis_emx2/directory_client/directory_client.py
molgenis_emx2/directory_client/errors.py
molgenis_emx2/directory_client/model.py
molgenis_emx2/directory_client/model_fitting.py
molgenis_emx2/directory_client/pid_manager.py
molgenis_emx2/directory_client/pid_service.py
molgenis_emx2/directory_client/printer.py
molgenis_emx2/directory_client/publication_preparer.py
molgenis_emx2/directory_client/publisher.py
molgenis_emx2/directory_client/stager.py
molgenis_emx2/directory_client/transformer.py
molgenis_emx2/directory_client/utils.py
molgenis_emx2/directory_client/validation.py
molgenis_emx2_directory_client-1.4.1.dist-info/licenses/AUTHORS.md
molgenis_emx2_directory_client-1.4.1.dist-info/licenses/LICENSE.txt
molgenis_emx2_directory_client-1.4.1.dist-info/METADATA
molgenis_emx2_directory_client-1.4.1.dist-info/WHEEL
molgenis_emx2_directory_client-1.4.1.dist-info/top_level.txt
molgenis_emx2_directory_client-1.4.1.dist-info/RECORD
