Metadata-Version: 2.4
Name: molgenis-emx2-directory-client
Version: 1.4.1
Summary: MOLGENIS EMX2 Python tooling for a BBMRI Biobank Directory
Home-page: https://github.com/molgenis/molgenis-emx2/tree/master/tools/directory/
Author: Dieuwke Roelofs-Prins
Author-email: support@molgenis.org
License: LGPL-3.0-only
Project-URL: Source, https://github.com/molgenis/molgenis-emx2/tree/master/tools/directory/
Platform: any
Classifier: License :: OSI Approved :: GNU Lesser General Public License v3 (LGPLv3)
Classifier: Programming Language :: Python
Classifier: Programming Language :: Python :: 3 :: Only
Classifier: Programming Language :: Python :: 3.10
Requires-Python: >=3.10
License-File: LICENSE.txt
License-File: AUTHORS.md
Requires-Dist: dataclasses
Requires-Dist: molgenis-emx2-pyclient
Requires-Dist: requests>=2.21.0
Requires-Dist: unidecode
Requires-Dist: pyhandle>=1.3.1
Provides-Extra: testing
Requires-Dist: setuptools; extra == "testing"
Requires-Dist: pytest; extra == "testing"
Requires-Dist: pytest-cov; extra == "testing"
Requires-Dist: pytest-asyncio; extra == "testing"
Requires-Dist: pytest-mock; extra == "testing"
Dynamic: license-file
